tests/__init__.py
tests/test_lengthConverter.py
tests/test_massConverter.py
tests/test_pressureConverter.py
tests/test_speedConverter.py
tests/test_tempConverter.py
tests/test_timeConverter.py
tests/test_volumeConverter.py
unitwise/__init__.py
unitwise/length.py
unitwise/mass.py
unitwise/pressure.py
unitwise/speed.py
unitwise/temperature.py
unitwise/time.py
unitwise/util.py
unitwise/volume.py
unitwise-0.0.6.dist-info/LICENSE.txt
unitwise-0.0.6.dist-info/METADATA
unitwise-0.0.6.dist-info/WHEEL
unitwise-0.0.6.dist-info/top_level.txt
unitwise-0.0.6.dist-info/RECORD
